fastapi_restkit/__init__.py
fastapi_restkit/config.py
fastapi_restkit/dependencies.py
fastapi_restkit/exceptions.py
fastapi_restkit/filters.py
fastapi_restkit/filterset.py
fastapi_restkit/models.py
fastapi_restkit/pagination.py
fastapi_restkit/py.typed
fastapi_restkit/sorting.py
fastapi_restkit/sortingset.py
fastapi_restkit/utils.py
fastapi_restkit-0.2.0.dist-info/licenses/LICENSE
fastapi_restkit-0.2.0.dist-info/WHEEL
fastapi_restkit-0.2.0.dist-info/METADATA
fastapi_restkit-0.2.0.dist-info/RECORD
