Metadata-Version: 2.4
Name: fastapi-restkit
Version: 0.2.0
Summary: Pagination utilities for FastAPI with SQLModel ORM
Keywords: fastapi,pagination,sqlmodel,rest,api,toolkit
Author: Fernando Cacenot
Author-email: Fernando Cacenot <cacenot@gmail.com>
License-Expression: MIT
License-File: LICENSE
Classifier: Development Status :: 3 - Alpha
Classifier: Framework :: FastAPI
Classifier: Intended Audience :: Developers
Classifier: License :: OSI Approved :: MIT License
Classifier: Programming Language :: Python :: 3
Classifier: Programming Language :: Python :: 3.10
Classifier: Programming Language :: Python :: 3.11
Classifier: Programming Language :: Python :: 3.12
Classifier: Programming Language :: Python :: 3.13
Classifier: Typing :: Typed
Requires-Dist: fastapi>=0.100.0
Requires-Dist: sqlmodel>=0.0.14
Requires-Dist: pytest>=7.0.0 ; extra == 'dev'
Requires-Dist: pytest-asyncio>=0.21.0 ; extra == 'dev'
Requires-Dist: httpx>=0.24.0 ; extra == 'dev'
Requires-Dist: ruff>=0.4.0 ; extra == 'dev'
Requires-Dist: mypy>=1.0.0 ; extra == 'dev'
Requires-Python: >=3.10
Project-URL: Homepage, https://github.com/cacenot/fastapi-restkit
Project-URL: Documentation, https://github.com/cacenot/fastapi-restkit#readme
Project-URL: Repository, https://github.com/cacenot/fastapi-restkit
Project-URL: Issues, https://github.com/cacenot/fastapi-restkit/issues
Provides-Extra: dev
